agent_control_models/__init__.py
agent_control_models/agent.py
agent_control_models/base.py
agent_control_models/controls.py
agent_control_models/errors.py
agent_control_models/evaluation.py
agent_control_models/evaluator.py
agent_control_models/health.py
agent_control_models/observability.py
agent_control_models/policy.py
agent_control_models/py.typed
agent_control_models/server.py
agent_control_models-3.0.0.dist-info/METADATA
agent_control_models-3.0.0.dist-info/WHEEL
agent_control_models-3.0.0.dist-info/RECORD
