Metadata-Version: 2.4
Name: agent-control-models
Version: 3.0.0
Summary: Shared data models for Agent Control server and SDK
Author: Agent Control Team
License: Apache-2.0
Requires-Python: >=3.12
Requires-Dist: jsonschema>=4.0.0
Requires-Dist: pydantic>=2.12.4
